cli/__init__.py
cli/an_es.py
cli/main.py
config/__init__.py
config/config.py
es_util/ESTOOL.py
es_util/__init__.py
log/LOG.py
log/__init__.py
report/__init__.py
alog_auto_viton-1.0.8.dist-info/METADATA
alog_auto_viton-1.0.8.dist-info/WHEEL
alog_auto_viton-1.0.8.dist-info/entry_points.txt
alog_auto_viton-1.0.8.dist-info/top_level.txt
alog_auto_viton-1.0.8.dist-info/RECORD
