Metadata-Version: 2.1
Name: alog-auto-viton
Version: 1.0.8
Requires-Dist: setuptools
Requires-Dist: requests
